tcx_extract/__init__.py
tcx_extract/build_zig.py
tcx_extract/extract.py
tcx_extract/zig/extract
tcx_extract/zig/extract.o
tcx_extract/zig/extract.zig
tcx_extract-0.1.2.dist-info/LICENSE
tcx_extract-0.1.2.dist-info/METADATA
tcx_extract-0.1.2.dist-info/WHEEL
tcx_extract-0.1.2.dist-info/entry_points.txt
tcx_extract-0.1.2.dist-info/top_level.txt
tcx_extract-0.1.2.dist-info/RECORD
