Metadata-Version: 2.1
Name: tcx_extract
Version: 0.1.2
Summary: A speed-optimized tcx data extractor.
Author-email: Alhan Keser <hello@alhan.co>
License-File: LICENSE
Requires-Dist: ziglang
